left/__init__.py
left/__main__.py
left/addons.py
left/app.py
left/controller.py
left/helpers.py
left/model.py
left/mountedview.py
left/router.py
left/sharedcomponents.py
left/splashscreen.py
left/view.py
left/database/__init__.py
left/database/documentdbresource.py
left/database/resourcelock.py
left/database/readonlydbservice/__init__.py
left/database/readonlydbservice/readonlydbresource.py
left/database/readonlydbservice/readonlydbservice.py
left/database/readonlydbservice/readonlyquerytools.py
left/database/tinydbservice/__init__.py
left/database/tinydbservice/tinydbresource.py
left/database/tinydbservice/tinydbservice.py
left/lefttest/__init__.py
left/lefttest/__main__.py
left/lefttest/testresult.py
left/lefttest/testrunner.py
left/lefttest/addon/__init__.py
left/lefttest/addon/testrunner/__init__.py
left/lefttest/addon/testrunner/controller.py
left/lefttest/addon/testrunner/views.py
python_left-0.0.9.dist-info/licenses/LICENSE
python_left-0.0.9.dist-info/METADATA
python_left-0.0.9.dist-info/WHEEL
python_left-0.0.9.dist-info/entry_points.txt
python_left-0.0.9.dist-info/top_level.txt
python_left-0.0.9.dist-info/RECORD
