Metadata-Version: 2.4
Name: python-left
Version: 0.0.9
Summary: A Minimalist Flet Framework
Home-page: 
Author: Nick Peck
Author-email: 
License: MIT License
Project-URL: Repository, https://github.com/nickpeck/left.git
Requires-Python: >=3.10
License-File: LICENSE
Requires-Dist: flet==0.27.6
Requires-Dist: dataclasses_json==0.6.3
Requires-Dist: tinydb==4.8.2
Requires-Dist: tinyrecord==0.2.0
Dynamic: license-file
Dynamic: requires-python
